setup.py
leafpy/__init__.py
leafpy/auth.py
leafpy/leaf.py
leafpy.egg-info/PKG-INFO
leafpy.egg-info/SOURCES.txt
leafpy.egg-info/dependency_links.txt
leafpy.egg-info/not-zip-safe
leafpy.egg-info/requires.txt
leafpy.egg-info/top_level.txt