Metadata-Version: 1.0
Name: leafpy
Version: 0.0.1
Summary: Lightweight python interface to the nissan leaf.
Home-page: https://github.com/nricklin/leafpy
Author: Nate Ricklin
Author-email: nate.ricklin@gmail.com
License: MIT
Platform: UNKNOWN
